{"docstore/data":{"6b3ab558-de52-4dbe-bb98-ef8b8ff99862":{"indexId":"6b3ab558-de52-4dbe-bb98-ef8b8ff99862","nodesDict":{"96049159-110d-433e-9160-d3f3f3bf1ffc":{"id_":"96049159-110d-433e-9160-d3f3f3bf1ffc","metadata":{},"excludedEmbedMetadataKeys":[],"excludedLlmMetadataKeys":[],"relationships":{"SOURCE":{"nodeId":"Dataset 20-9-67/GPU_ASROCK.txt","metadata":{},"hash":"SvY+vxocQHssPLCaCkFO3gAc3mYmvAT9k25pFwBL4TQ="}},"text":"Name: ASROCK INTEL ARC A750 CHALLENGER D 8GB OC - 8GB GDDR6 (A750 CLD 8GO)\r\nPrice: 11500 THB\r\nSlot: 1 x PCIe 4.0 x16 Slot\r\nChipset: Intel\r\nSeries: Intel Arc A-series\r\nGraphic Engine: Arc A750\r\nVideo Memory Capacity: 8 GB\r\nTypes of Video Memory: GDDR6\r\nDimension: 271 x  132  x 48 mm \r\nNeed Power Supply: 650 W\r\nPower Connectors: 2 x 8 Pin\r\n--------------------------------------","textTemplate":"","metadataSeparator":"\n","type":"TEXT","hash":"rXovEhXn8jlsWnZipG29z5fx3FYQ1UsWhkuZGjZsmyU="}},"type":"simple_dict"}}}